{"_id":{"$oid":"5c5a4147e988da5df81cd190"},"columnId":"10000","columnList":[{"_id":{"$oid":"5c5a4147e988da5df81cd1af"},"linkAddress":"javascript:;","name":"新闻"},{"_id":{"$oid":"5c5a4147e988da5df81cd1ae"},"linkAddress":"javascript:;","name":"娱乐"},{"_id":{"$oid":"5c5a4147e988da5df81cd1ad"},"linkAddress":"javascript:;","name":"体育"},{"_id":{"$oid":"5c5a4147e988da5df81cd1ac"},"linkAddress":"javascript:;","name":"财经"},{"_id":{"$oid":"5c5a4147e988da5df81cd1ab"},"linkAddress":"javascript:;","name":"图片"},{"_id":{"$oid":"5c5a4147e988da5df81cd1aa"},"linkAddress":"javascript:;","name":"汽车"},{"_id":{"$oid":"5c5a4147e988da5df81cd1a9"},"linkAddress":"javascript:;","name":"星闻"},{"_id":{"$oid":"5c5a4147e988da5df81cd1a8"},"linkAddress":"javascript:;","name":"军事"},{"_id":{"$oid":"5c5a4147e988da5df81cd1a7"},"linkAddress":"javascript:;","name":"直播"},{"_id":{"$oid":"5c5a4147e988da5df81cd1a6"},"linkAddress":"javascript:;","name":"视频"},{"_id":{"$oid":"5c5a4147e988da5df81cd1a5"},"linkAddress":"javascript:;","name":"科技"},{"_id":{"$oid":"5c5a4147e988da5df81cd1a4"},"linkAddress":"javascript:;","name":"手机"},{"_id":{"$oid":"5c5a4147e988da5df81cd1a3"},"linkAddress":"javascript:;","name":"数码"},{"_id":{"$oid":"5c5a4147e988da5df81cd1a2"},"linkAddress":"javascript:;","name":"本地"},{"_id":{"$oid":"5c5a4147e988da5df81cd1a1"},"linkAddress":"javascript:;","name":"网易号"},{"_id":{"$oid":"5c5a4147e988da5df81cd1a0"},"linkAddress":"javascript:;","name":"段子"},{"_id":{"$oid":"5c5a4147e988da5df81cd19f"},"linkAddress":"javascript:;","name":"时尚"},{"_id":{"$oid":"5c5a4147e988da5df81cd19e"},"linkAddress":"javascript:;","name":"跟贴"},{"_id":{"$oid":"5c5a4147e988da5df81cd19d"},"linkAddress":"javascript:;","name":"游戏"},{"_id":{"$oid":"5c5a4147e988da5df81cd19c"},"linkAddress":"javascript:;","name":"教育"},{"_id":{"$oid":"5c5a4147e988da5df81cd19b"},"linkAddress":"javascript:;","name":"公开课"},{"_id":{"$oid":"5c5a4147e988da5df81cd19a"},"linkAddress":"javascript:;","name":"健康"},{"_id":{"$oid":"5c5a4147e988da5df81cd199"},"linkAddress":"javascript:;","name":"独家"},{"_id":{"$oid":"5c5a4147e988da5df81cd198"},"linkAddress":"javascript:;","name":"旅游"},{"_id":{"$oid":"5c5a4147e988da5df81cd197"},"linkAddress":"javascript:;","name":"亲子"},{"_id":{"$oid":"5c5a4147e988da5df81cd196"},"linkAddress":"javascript:;","name":"艺术"},{"_id":{"$oid":"5c5a4147e988da5df81cd195"},"linkAddress":"javascript:;","name":"双创"},{"_id":{"$oid":"5c5a4147e988da5df81cd194"},"linkAddress":"javascript:;","name":"房产"},{"_id":{"$oid":"5c5a4147e988da5df81cd193"},"linkAddress":"javascript:;","name":"家居"},{"_id":{"$oid":"5c5a4147e988da5df81cd192"},"linkAddress":"javascript:;","name":"酒香"},{"_id":{"$oid":"5c5a4147e988da5df81cd191"},"linkAddress":"javascript:;","name":"航空"}],"__v":0}
